{
    "info": {
        "title": "Avi PoolGroupDeploymentPolicy Object API", 
        "version": "17.2.3", 
        "description": "##CLI##\n```\n- configure poolgroupdeploymentpolicy <key>\n- show poolgroupdeploymentpolicy <key>\n```\n", 
        "contact": {
            "url": "https://avinetworks.com/contact-us", 
            "name": "Avi Networks Inc.", 
            "email": "support@avinetworks.com"
        }
    }, 
    "paths": {
        "/poolgroupdeploymentpolicy": {
            "post": {
                "security": [
                    {
                        "basicAuth": []
                    }
                ], 
                "produces": [
                    "application/json"
                ], 
                "responses": {
                    "200": {
                        "description": "OK", 
                        "schema": {
                            "$ref": "#/definitions/PoolGroupDeploymentPolicy"
                        }
                    }, 
                    "401": {
                        "description": "log in failed"
                    }
                }, 
                "parameters": [
                    {
                        "required": false, 
                        "type": "string", 
                        "description": "Avi Tenant Header", 
                        "in": "header", 
                        "name": "X-Avi-Tenant"
                    }, 
                    {
                        "required": false, 
                        "type": "string", 
                        "description": "Avi Tenant Header UUID", 
                        "in": "header", 
                        "name": "X-Avi-Tenant-UUID"
                    }, 
                    {
                        "required": true, 
                        "type": "string", 
                        "description": "The caller is required to set Avi Version Header to the expected version of configuration. If unset, the version will be defaulted to 16.4.3. The response from the controller will provide and accept data according to the specified version. The controller will reject POST and PUT requests where the data is not compatible with the specified version.", 
                        "in": "header", 
                        "name": "X-Avi-Version"
                    }, 
                    {
                        "required": false, 
                        "type": "string", 
                        "description": "Avi Controller may send back CSRF token in the response cookies. The caller should update the request headers with this token else controller will reject requests.", 
                        "in": "header", 
                        "name": "X-CSRFToken"
                    }, 
                    {
                        "required": true, 
                        "in": "body", 
                        "description": "PoolGroupDeploymentPolicy object creation", 
                        "name": "body", 
                        "schema": {
                            "$ref": "#/definitions/PoolGroupDeploymentPolicy"
                        }
                    }
                ], 
                "consumes": [
                    "application/json"
                ]
            }, 
            "get": {
                "security": [
                    {
                        "basicAuth": []
                    }
                ], 
                "produces": [
                    "application/json"
                ], 
                "responses": {
                    "200": {
                        "description": "OK", 
                        "schema": {
                            "$ref": "#/definitions/PoolGroupDeploymentPolicyApiResponse"
                        }
                    }, 
                    "401": {
                        "description": "log in failed"
                    }
                }, 
                "parameters": [
                    {
                        "required": false, 
                        "type": "string", 
                        "description": "object name", 
                        "in": "query", 
                        "name": "name"
                    }, 
                    {
                        "in": "query", 
                        "type": "string", 
                        "description": "Filter to request all objects that refers to another Avi resource. Its syntax is refers_to=<obj_type>:<obj_uuid>. Eg. get all virtual services referring to pool p1 will be refers_to=pool:pool_p1_uuid", 
                        "name": "refers_to"
                    }, 
                    {
                        "in": "query", 
                        "type": "string", 
                        "description": "Filter to request all objects that are referred by another Avi resource. Its syntax is referred_by=<obj_type>:<obj_uuid>. Eg. get all pools referred_by virtual service vs1 - referred_by=virtualservice:vs_vs1_uuid", 
                        "name": "referred_by"
                    }, 
                    {
                        "in": "query", 
                        "type": "string", 
                        "description": "List of fields to be returned for the resource. Some fields like name, URL, uuid etc. are always returned.", 
                        "name": "fields"
                    }, 
                    {
                        "in": "query", 
                        "type": "string", 
                        "description": "All the Avi REST reference URIs have a name suffix as URI#name. It is useful to get the referenced resource name without performing get on that object.", 
                        "name": "include_name"
                    }, 
                    {
                        "in": "query", 
                        "type": "string", 
                        "description": "It automatically returns additional dependent resources like runtime. Eg. join_subresources=runtime.", 
                        "name": "join_subresources"
                    }, 
                    {
                        "required": false, 
                        "type": "string", 
                        "description": "Avi Tenant Header", 
                        "in": "header", 
                        "name": "X-Avi-Tenant"
                    }, 
                    {
                        "required": false, 
                        "type": "string", 
                        "description": "Avi Tenant Header UUID", 
                        "in": "header", 
                        "name": "X-Avi-Tenant-UUID"
                    }, 
                    {
                        "required": true, 
                        "type": "string", 
                        "description": "The caller is required to set Avi Version Header to the expected version of configuration. If unset, the version will be defaulted to 16.4.3. The response from the controller will provide and accept data according to the specified version. The controller will reject POST and PUT requests where the data is not compatible with the specified version.", 
                        "in": "header", 
                        "name": "X-Avi-Version"
                    }, 
                    {
                        "required": false, 
                        "type": "string", 
                        "description": "Avi Controller may send back CSRF token in the response cookies. The caller should update the request headers with this token else controller will reject requests.", 
                        "in": "header", 
                        "name": "X-CSRFToken"
                    }, 
                    {
                        "in": "query", 
                        "type": "string", 
                        "description": "Filter to get objects that belongs to a specific cloud using its uuid. Eg. cloud_uuid=cloud-xyz.", 
                        "name": "cloud_uuid"
                    }, 
                    {
                        "in": "query", 
                        "type": "string", 
                        "description": "Filter to get objects that belongs to a specific cloud usings its name. This uses cloud name rather than uuid. Eg. cloud_ref.name=Default-Cloud.", 
                        "name": "cloud_ref.name"
                    }
                ], 
                "consumes": [
                    "application/json"
                ]
            }
        }, 
        "/poolgroupdeploymentpolicy/{uuid}": {
            "put": {
                "security": [
                    {
                        "basicAuth": []
                    }
                ], 
                "produces": [
                    "application/json"
                ], 
                "responses": {
                    "200": {
                        "description": "OK", 
                        "schema": {
                            "$ref": "#/definitions/PoolGroupDeploymentPolicy"
                        }
                    }, 
                    "401": {
                        "description": "log in failed"
                    }
                }, 
                "parameters": [
                    {
                        "required": false, 
                        "type": "string", 
                        "description": "object name", 
                        "in": "query", 
                        "name": "name"
                    }, 
                    {
                        "required": false, 
                        "type": "string", 
                        "description": "Avi Tenant Header", 
                        "in": "header", 
                        "name": "X-Avi-Tenant"
                    }, 
                    {
                        "required": false, 
                        "type": "string", 
                        "description": "Avi Tenant Header UUID", 
                        "in": "header", 
                        "name": "X-Avi-Tenant-UUID"
                    }, 
                    {
                        "required": true, 
                        "type": "string", 
                        "description": "The caller is required to set Avi Version Header to the expected version of configuration. If unset, the version will be defaulted to 16.4.3. The response from the controller will provide and accept data according to the specified version. The controller will reject POST and PUT requests where the data is not compatible with the specified version.", 
                        "in": "header", 
                        "name": "X-Avi-Version"
                    }, 
                    {
                        "required": false, 
                        "type": "string", 
                        "description": "Avi Controller may send back CSRF token in the response cookies. The caller should update the request headers with this token else controller will reject requests.", 
                        "in": "header", 
                        "name": "X-CSRFToken"
                    }, 
                    {
                        "required": true, 
                        "in": "body", 
                        "description": "PoolGroupDeploymentPolicy object creation", 
                        "name": "body", 
                        "schema": {
                            "$ref": "#/definitions/PoolGroupDeploymentPolicy"
                        }
                    }, 
                    {
                        "required": true, 
                        "type": "string", 
                        "description": "UUID of the object to fetch", 
                        "in": "path", 
                        "name": "uuid"
                    }
                ], 
                "consumes": [
                    "application/json"
                ]
            }, 
            "get": {
                "security": [
                    {
                        "basicAuth": []
                    }
                ], 
                "produces": [
                    "application/json"
                ], 
                "responses": {
                    "200": {
                        "description": "OK", 
                        "schema": {
                            "$ref": "#/definitions/PoolGroupDeploymentPolicy"
                        }
                    }, 
                    "401": {
                        "description": "log in failed"
                    }
                }, 
                "parameters": [
                    {
                        "required": false, 
                        "type": "string", 
                        "description": "object name", 
                        "in": "query", 
                        "name": "name"
                    }, 
                    {
                        "required": false, 
                        "type": "string", 
                        "description": "Avi Tenant Header", 
                        "in": "header", 
                        "name": "X-Avi-Tenant"
                    }, 
                    {
                        "required": false, 
                        "type": "string", 
                        "description": "Avi Tenant Header UUID", 
                        "in": "header", 
                        "name": "X-Avi-Tenant-UUID"
                    }, 
                    {
                        "required": true, 
                        "type": "string", 
                        "description": "The caller is required to set Avi Version Header to the expected version of configuration. If unset, the version will be defaulted to 16.4.3. The response from the controller will provide and accept data according to the specified version. The controller will reject POST and PUT requests where the data is not compatible with the specified version.", 
                        "in": "header", 
                        "name": "X-Avi-Version"
                    }, 
                    {
                        "required": false, 
                        "type": "string", 
                        "description": "Avi Controller may send back CSRF token in the response cookies. The caller should update the request headers with this token else controller will reject requests.", 
                        "in": "header", 
                        "name": "X-CSRFToken"
                    }, 
                    {
                        "required": true, 
                        "type": "string", 
                        "description": "UUID of the object to fetch", 
                        "in": "path", 
                        "name": "uuid"
                    }, 
                    {
                        "in": "query", 
                        "type": "string", 
                        "description": "List of fields to be returned for the resource. Some fields like name, URL, uuid etc. are always returned.", 
                        "name": "fields"
                    }, 
                    {
                        "in": "query", 
                        "type": "string", 
                        "description": "All the Avi REST reference URIs have a name suffix as URI#name. It is useful to get the referenced resource name without performing get on that object.", 
                        "name": "include_name"
                    }, 
                    {
                        "in": "query", 
                        "type": "string", 
                        "description": "It automatically returns additional dependent resources like runtime. Eg. join_subresources=runtime.", 
                        "name": "join_subresources"
                    }
                ], 
                "consumes": [
                    "application/json"
                ]
            }, 
            "patch": {
                "security": [
                    {
                        "basicAuth": []
                    }
                ], 
                "produces": [
                    "application/json"
                ], 
                "responses": {
                    "200": {
                        "description": "OK", 
                        "schema": {
                            "$ref": "#/definitions/PoolGroupDeploymentPolicy"
                        }
                    }, 
                    "401": {
                        "description": "log in failed"
                    }
                }, 
                "parameters": [
                    {
                        "required": false, 
                        "type": "string", 
                        "description": "object name", 
                        "in": "query", 
                        "name": "name"
                    }, 
                    {
                        "required": false, 
                        "type": "string", 
                        "description": "Avi Tenant Header", 
                        "in": "header", 
                        "name": "X-Avi-Tenant"
                    }, 
                    {
                        "required": false, 
                        "type": "string", 
                        "description": "Avi Tenant Header UUID", 
                        "in": "header", 
                        "name": "X-Avi-Tenant-UUID"
                    }, 
                    {
                        "required": true, 
                        "type": "string", 
                        "description": "The caller is required to set Avi Version Header to the expected version of configuration. If unset, the version will be defaulted to 16.4.3. The response from the controller will provide and accept data according to the specified version. The controller will reject POST and PUT requests where the data is not compatible with the specified version.", 
                        "in": "header", 
                        "name": "X-Avi-Version"
                    }, 
                    {
                        "required": false, 
                        "type": "string", 
                        "description": "Avi Controller may send back CSRF token in the response cookies. The caller should update the request headers with this token else controller will reject requests.", 
                        "in": "header", 
                        "name": "X-CSRFToken"
                    }, 
                    {
                        "required": true, 
                        "in": "body", 
                        "description": "PoolGroupDeploymentPolicy object creation", 
                        "name": "body", 
                        "schema": {
                            "$ref": "#/definitions/PoolGroupDeploymentPolicy"
                        }
                    }, 
                    {
                        "required": true, 
                        "type": "string", 
                        "description": "UUID of the object to fetch", 
                        "in": "path", 
                        "name": "uuid"
                    }
                ], 
                "consumes": [
                    "application/json"
                ]
            }, 
            "delete": {
                "security": [
                    {
                        "basicAuth": []
                    }
                ], 
                "produces": [
                    "application/json"
                ], 
                "responses": {
                    "204": {
                        "description": "object deleted", 
                        "schema": {
                            "type": "string"
                        }
                    }, 
                    "404": {
                        "description": "not found"
                    }
                }, 
                "parameters": [
                    {
                        "required": false, 
                        "type": "string", 
                        "description": "object name", 
                        "in": "query", 
                        "name": "name"
                    }, 
                    {
                        "required": false, 
                        "type": "string", 
                        "description": "Avi Tenant Header", 
                        "in": "header", 
                        "name": "X-Avi-Tenant"
                    }, 
                    {
                        "required": false, 
                        "type": "string", 
                        "description": "Avi Tenant Header UUID", 
                        "in": "header", 
                        "name": "X-Avi-Tenant-UUID"
                    }, 
                    {
                        "required": true, 
                        "type": "string", 
                        "description": "The caller is required to set Avi Version Header to the expected version of configuration. If unset, the version will be defaulted to 16.4.3. The response from the controller will provide and accept data according to the specified version. The controller will reject POST and PUT requests where the data is not compatible with the specified version.", 
                        "in": "header", 
                        "name": "X-Avi-Version"
                    }, 
                    {
                        "required": false, 
                        "type": "string", 
                        "description": "Avi Controller may send back CSRF token in the response cookies. The caller should update the request headers with this token else controller will reject requests.", 
                        "in": "header", 
                        "name": "X-CSRFToken"
                    }, 
                    {
                        "required": true, 
                        "type": "string", 
                        "description": "UUID of the object to fetch", 
                        "in": "path", 
                        "name": "uuid"
                    }
                ], 
                "consumes": [
                    "application/json"
                ]
            }
        }
    }, 
    "definitions": {
        "PGDeploymentRule": {
            "type": "object", 
            "properties": {
                "operator": {
                    "default": "CO_GE", 
                    "type": "string", 
                    "description": " Enum options - CO_EQ, CO_GT, CO_GE, CO_LT, CO_LE, CO_NE."
                }, 
                "threshold": {
                    "type": "number", 
                    "description": "metric threshold that is used as the pass fail. If it is not provided then it will simply compare it with current pool vs new pool.", 
                    "format": "double"
                }, 
                "metric_id": {
                    "default": "health.health_score_value", 
                    "type": "string", 
                    "description": "metric_id of PGDeploymentRule."
                }
            }
        }, 
        "PoolGroupDeploymentPolicy": {
            "required": [
                "name"
            ], 
            "type": "object", 
            "properties": {
                "target_test_traffic_ratio": {
                    "default": 100, 
                    "type": "integer", 
                    "description": "Target traffic ratio before pool is made production. Allowed values are 1-100.", 
                    "format": "int32"
                }, 
                "evaluation_duration": {
                    "default": 300, 
                    "type": "integer", 
                    "description": "Duration of evaluation period for automatic deployment. Allowed values are 60-86400.", 
                    "format": "int32"
                }, 
                "description": {
                    "type": "string", 
                    "description": "User defined description for the object."
                }, 
                "test_traffic_ratio_rampup": {
                    "default": 100, 
                    "type": "integer", 
                    "description": "Ratio of the traffic that is sent to the pool under test. test ratio of 100 means blue green. Allowed values are 1-100.", 
                    "format": "int32"
                }, 
                "cloud_ref": {
                    "type": "string", 
                    "description": " It is a reference to an object of type Cloud."
                }, 
                "auto_disable_old_prod_pools": {
                    "default": true, 
                    "type": "boolean", 
                    "description": "It will automatically disable old production pools once there is a new production candidate."
                }, 
                "tenant_ref": {
                    "type": "string", 
                    "description": " It is a reference to an object of type Tenant."
                }, 
                "name": {
                    "type": "string", 
                    "description": "The name of the pool group deployment policy."
                }, 
                "rules": {
                    "items": {
                        "$ref": "#/definitions/PGDeploymentRule"
                    }, 
                    "type": "array", 
                    "description": "Placeholder for description of property rules of obj type PoolGroupDeploymentPolicy field type str  type object"
                }, 
                "url": {
                    "readOnly": true, 
                    "type": "string", 
                    "description": "url"
                }, 
                "webhook_ref": {
                    "type": "string", 
                    "description": "Webhook configured with URL that Avi controller will pass back information about pool group, old and new pool information and current deployment rule results. It is a reference to an object of type Webhook. Field introduced in 17.1.1."
                }, 
                "scheme": {
                    "default": "BLUE_GREEN", 
                    "type": "string", 
                    "description": "deployment scheme. Enum options - BLUE_GREEN, CANARY."
                }, 
                "uuid": {
                    "type": "string", 
                    "description": "UUID of the pool group deployment policy."
                }
            }
        }, 
        "PoolGroupDeploymentPolicyApiResponse": {
            "required": [
                "count", 
                "results"
            ], 
            "type": "object", 
            "properties": {
                "count": {
                    "type": "integer", 
                    "format": "int32"
                }, 
                "results": {
                    "items": {
                        "$ref": "#/definitions/PoolGroupDeploymentPolicy"
                    }, 
                    "type": "array"
                }
            }
        }
    }, 
    "basePath": "/api", 
    "swagger": "2.0", 
    "securityDefinitions": {
        "basicAuth": {
            "type": "basic", 
            "description": "basic authentication"
        }
    }
}